pytzkt/__init__.py
pytzkt/api.py
pytzkt-0.1.1.dist-info/LICENSE
pytzkt-0.1.1.dist-info/WHEEL
pytzkt-0.1.1.dist-info/METADATA
pytzkt-0.1.1.dist-info/RECORD
