Metadata-Version: 2.1
Name: pytzkt
Version: 0.1.1
Summary: TzKT API wrapper
Author: AO
Author-email: aopoltorzhicky@gmail.com
Requires-Python: >=3.7,<4.0
Classifier: Programming Language :: Python :: 3
Classifier: Programming Language :: Python :: 3.7
